nappo/__init__.py
nappo/learner.py
nappo/utils.py
nappo/core/__init__.py
nappo/core/actors/__init__.py
nappo/core/actors/base.py
nappo/core/actors/off_policy_actor_critic.py
nappo/core/actors/on_policy_actor_critic.py
nappo/core/actors/utils.py
nappo/core/actors/distributions/__init__.py
nappo/core/actors/distributions/categorical.py
nappo/core/actors/distributions/gaussian.py
nappo/core/actors/distributions/squashed_gaussian.py
nappo/core/actors/neural_networks/__init__.py
nappo/core/actors/neural_networks/neural_network.py
nappo/core/actors/neural_networks/feature_extractors/__init__.py
nappo/core/actors/neural_networks/feature_extractors/cnn.py
nappo/core/actors/neural_networks/feature_extractors/fixup_cnn.py
nappo/core/actors/neural_networks/feature_extractors/mlp.py
nappo/core/actors/neural_networks/feature_extractors/utils.py
nappo/core/algos/__init__.py
nappo/core/algos/base.py
nappo/core/algos/ddqn.py
nappo/core/algos/ppo.py
nappo/core/algos/sac.py
nappo/core/algos/vpg.py
nappo/core/env/__init__.py
nappo/core/env/env_wrappers.py
nappo/core/env/vec_env.py
nappo/core/env/vector_wrappers.py
nappo/core/storages/__init__.py
nappo/core/storages/base.py
nappo/core/storages/off_policy/__init__.py
nappo/core/storages/off_policy/hindsight_experience_replay_buffer.py
nappo/core/storages/off_policy/replay_buffer.py
nappo/core/storages/on_policy/__init__.py
nappo/core/storages/on_policy/on_policy_buffer.py
nappo/core/storages/on_policy/on_policy_gae_buffer.py
nappo/core/storages/on_policy/on_policy_vtrace_buffer.py
nappo/envs/__init__.py
nappo/envs/common.py
nappo/envs/atari/__init__.py
nappo/envs/atari/atari_env_factory.py
nappo/envs/atari/wrappers.py
nappo/envs/mujoco/__init__.py
nappo/envs/mujoco/mujoco_env_factory.py
nappo/envs/obstacle_tower_unity3d_challenge/__init__.py
nappo/envs/obstacle_tower_unity3d_challenge/obstacle_tower_env_factory.py
nappo/envs/obstacle_tower_unity3d_challenge/utils.py
nappo/envs/obstacle_tower_unity3d_challenge/wrappers.py
nappo-0.0.44.dist-info/LICENCE
nappo-0.0.44.dist-info/METADATA
nappo-0.0.44.dist-info/WHEEL
nappo-0.0.44.dist-info/top_level.txt
nappo-0.0.44.dist-info/RECORD
