Metadata-Version: 2.1
Name: nappo
Version: 0.0.44
Summary: Disributed RL implementations with ray and pytorch.
Home-page: https://github.com/nappo/nappo/
Author: 
Author-email: 
License: UNKNOWN
Platform: UNKNOWN
Classifier: Programming Language :: Python :: 3
Classifier: License :: OSI Approved :: MIT License
Classifier: Operating System :: OS Independent
Requires-Dist: ray
Requires-Dist: ray[debug]
Requires-Dist: pybullet
Requires-Dist: Tensorflow
Requires-Dist: TensorBoard
